{
	"connection_key": "response",
	"result": true,
	"redis_key": "abcdefg",
	"filepath": "/var/lib/aion/Data/rededge_sdc/abcdef.json",
	"ProfitCenter": {
		"ControllingArea": "0001",
		"ProfitCenter": "100000",
		"ValidityEndDate": "",
		"ProfitCtrResponsiblePersonName": "",
		"CompanyCode": "",
		"ProfitCtrResponsibleUser": "",
		"ValidityStartDate": "",
		"Department": "",
		"ProfitCenterStandardHierarchy": "",
		"Segment": "",
		"ProfitCenterIsBlocked": "",
		"FormulaPlanningTemplate": "",
		"FormOfAddress": "",
		"AddressName": "",
		"AdditionalName": "",
		"ProfitCenterAddrName3": "",
		"ProfitCenterAddrName4": "",
		"StreetAddressName": "",
		"POBox": "",
		"CityName": "",
		"PostalCode": "",
		"District": "",
		"Country": "",
		"Region": "",
		"TaxJurisdiction": "",
		"Language": "",
		"PhoneNumber1": "",
		"PhoneNumber2": "",
		"TeleboxNumber": "",
		"TelexNumber": "",
		"FaxNumber": "",
		"DataCommunicationPhoneNumber": "",
		"ProfitCenterPrinterName": "",
		"ProfitCenterCreatedByUser": "",
		"ProfitCenterCreationDate": "",
		"YY1_LOB_PRC": "",
		"Text": {
			"Language": "",
			"ValidityEndDate": "",
			"ValidityStartDate": "",
			"ProfitCenterName": "",
			"ProfitCenterLongName": ""
		},
		"CompanyCodeAssignment": {
			"CompanyCode": ""
		}
	},
	"api_schema": "SAPProfitCenterReads",
	"accepter": ["Header"],
	"profit_center_code": "100000",
	"deleted": false
}
